{
    "js": [
        "js/dataTables.bootstrap5.js",
        "js/dataTables.bootstrap5.min.js",
        "js/dataTables.bootstrap5.min.mjs",
        "js/dataTables.bootstrap5.mjs"
    ],
    "css": [
        "css/dataTables.bootstrap5.css",
        "css/dataTables.bootstrap5.min.css"
    ],
    "types": [
        "types/dataTables.bootstrap5.d.ts"
    ],
    "src-repo": "http://github.com/DataTables/DataTablesSrc",
    "last-tag": "2.0.2",
    "last-sync": "193bd5951d08d65cc50c25c01e3d6ced62121aaf"
}